YCPyLib/YCPyLib.py
YCPyLib/__init__.py
YCPyLib-0.0.2.dist-info/METADATA
YCPyLib-0.0.2.dist-info/WHEEL
YCPyLib-0.0.2.dist-info/top_level.txt
YCPyLib-0.0.2.dist-info/RECORD
